jsonargparse/__init__.py
jsonargparse/_actions.py
jsonargparse/_cli.py
jsonargparse/_common.py
jsonargparse/_completions.py
jsonargparse/_core.py
jsonargparse/_deprecated.py
jsonargparse/_formatters.py
jsonargparse/_from_config.py
jsonargparse/_jsonnet.py
jsonargparse/_jsonschema.py
jsonargparse/_link_arguments.py
jsonargparse/_loaders_dumpers.py
jsonargparse/_namespace.py
jsonargparse/_optionals.py
jsonargparse/_parameter_resolvers.py
jsonargparse/_paths.py
jsonargparse/_postponed_annotations.py
jsonargparse/_signatures.py
jsonargparse/_stubs_resolver.py
jsonargparse/_type_checking.py
jsonargparse/_typehints.py
jsonargparse/_util.py
jsonargparse/py.typed
jsonargparse/typing.py
jsonargparse-4.45.0.dist-info/licenses/LICENSE.rst
jsonargparse_tests/__init__.py
jsonargparse_tests/__main__.py
jsonargparse_tests/conftest.py
jsonargparse_tests/test_actions.py
jsonargparse_tests/test_argcomplete.py
jsonargparse_tests/test_attrs.py
jsonargparse_tests/test_cli.py
jsonargparse_tests/test_core.py
jsonargparse_tests/test_dataclasses.py
jsonargparse_tests/test_deprecated.py
jsonargparse_tests/test_final_classes.py
jsonargparse_tests/test_formatters.py
jsonargparse_tests/test_from_config.py
jsonargparse_tests/test_jsonnet.py
jsonargparse_tests/test_jsonschema.py
jsonargparse_tests/test_link_arguments.py
jsonargparse_tests/test_loaders_dumpers.py
jsonargparse_tests/test_namespace.py
jsonargparse_tests/test_omegaconf.py
jsonargparse_tests/test_optionals.py
jsonargparse_tests/test_parameter_resolvers.py
jsonargparse_tests/test_parsing_settings.py
jsonargparse_tests/test_paths.py
jsonargparse_tests/test_postponed_annotations.py
jsonargparse_tests/test_pydantic.py
jsonargparse_tests/test_shtab.py
jsonargparse_tests/test_signatures.py
jsonargparse_tests/test_stubs_resolver.py
jsonargparse_tests/test_subclasses.py
jsonargparse_tests/test_subcommands.py
jsonargparse_tests/test_typehints.py
jsonargparse_tests/test_typing.py
jsonargparse_tests/test_util.py
jsonargparse-4.45.0.dist-info/METADATA
jsonargparse-4.45.0.dist-info/WHEEL
jsonargparse-4.45.0.dist-info/top_level.txt
jsonargparse-4.45.0.dist-info/RECORD
