Metadata-Version: 2.4
Name: jsonargparse
Version: 4.45.0
Summary: Minimal effort CLIs derived from type hints and parse from command line, config files and environment variables.
Author-email: Mauricio Villegas <mauricio@omnius.com>
License-Expression: MIT
Project-URL: Documentation-stable, https://jsonargparse.readthedocs.io/en/stable/
Project-URL: Documentation-latest, https://jsonargparse.readthedocs.io/en/latest/
Project-URL: Changes, https://jsonargparse.readthedocs.io/en/stable/changelog.html
Project-URL: GitHub, https://github.com/omni-us/jsonargparse
Project-URL: PyPI, https://pypi.org/project/jsonargparse
Project-URL: SonarCloud, https://sonarcloud.io/dashboard?id=omni-us_jsonargparse
Project-URL: Codecov, https://codecov.io/gh/omni-us/jsonargparse
Platform: Any
Classifier: Development Status :: 5 - Production/Stable
Classifier: Programming Language :: Python
Classifier: Programming Language :: Python :: 3
Classifier: Programming Language :: Python :: 3 :: Only
Classifier: Programming Language :: Python :: 3.9
Classifier: Programming Language :: Python :: 3.10
Classifier: Programming Language :: Python :: 3.11
Classifier: Programming Language :: Python :: 3.12
Classifier: Programming Language :: Python :: 3.13
Classifier: Programming Language :: Python :: 3.14
Classifier: Intended Audience :: Developers
Classifier: Operating System :: POSIX :: Linux
Classifier: Operating System :: MacOS
Classifier: Operating System :: Microsoft :: Windows
Requires-Python: >=3.9
License-File: LICENSE.rst
Requires-Dist: PyYAML>=3.13
Provides-Extra: all
Requires-Dist: jsonargparse[signatures]; extra == "all"
Requires-Dist: jsonargparse[jsonschema]; extra == "all"
Requires-Dist: jsonargparse[jsonnet]; extra == "all"
Requires-Dist: jsonargparse[toml]; extra == "all"
Requires-Dist: jsonargparse[urls]; extra == "all"
Requires-Dist: jsonargparse[fsspec]; extra == "all"
Requires-Dist: jsonargparse[ruamel]; extra == "all"
Requires-Dist: jsonargparse[omegaconf]; extra == "all"
Requires-Dist: jsonargparse[typing-extensions]; extra == "all"
Requires-Dist: jsonargparse[reconplogger]; extra == "all"
Provides-Extra: signatures
Requires-Dist: jsonargparse[typing-extensions]; extra == "signatures"
Requires-Dist: docstring-parser>=0.17; extra == "signatures"
Requires-Dist: typeshed-client>=2.8.2; extra == "signatures"
Provides-Extra: jsonschema
Requires-Dist: jsonschema>=3.2.0; extra == "jsonschema"
Provides-Extra: jsonnet
Requires-Dist: jsonnet>=0.21.0; extra == "jsonnet"
Provides-Extra: toml
Requires-Dist: toml>=0.10.2; extra == "toml"
Provides-Extra: urls
Requires-Dist: requests>=2.18.4; extra == "urls"
Provides-Extra: fsspec
Requires-Dist: fsspec>=0.8.4; extra == "fsspec"
Provides-Extra: shtab
Requires-Dist: shtab>=1.7.1; extra == "shtab"
Provides-Extra: argcomplete
Requires-Dist: argcomplete>=3.5.1; extra == "argcomplete"
Provides-Extra: ruamel
Requires-Dist: ruamel.yaml>=0.18.15; extra == "ruamel"
Provides-Extra: ruyaml
Requires-Dist: jsonargparse[ruamel]; extra == "ruyaml"
Provides-Extra: omegaconf
Requires-Dist: omegaconf>=2.1.1; extra == "omegaconf"
Provides-Extra: typing-extensions
Requires-Dist: typing-extensions>=3.10.0.0; python_version < "3.10" and extra == "typing-extensions"
Provides-Extra: reconplogger
Requires-Dist: reconplogger>=4.4.0; extra == "reconplogger"
Provides-Extra: test
Requires-Dist: jsonargparse[test-no-urls]; extra == "test"
Requires-Dist: jsonargparse[shtab]; extra == "test"
Requires-Dist: jsonargparse[argcomplete]; extra == "test"
Requires-Dist: types-PyYAML>=6.0.11; extra == "test"
Requires-Dist: types-requests>=2.28.9; extra == "test"
Requires-Dist: responses>=0.12.0; extra == "test"
Requires-Dist: pydantic>=2.3.0; extra == "test"
Requires-Dist: attrs>=22.2.0; extra == "test"
Provides-Extra: test-no-urls
Requires-Dist: pytest>=6.2.5; extra == "test-no-urls"
Requires-Dist: pytest-subtests>=0.8.0; extra == "test-no-urls"
Provides-Extra: coverage
Requires-Dist: jsonargparse[test-no-urls]; extra == "coverage"
Requires-Dist: pytest-cov>=4.0.0; extra == "coverage"
Provides-Extra: dev
Requires-Dist: jsonargparse[test]; extra == "dev"
Requires-Dist: jsonargparse[coverage]; extra == "dev"
Requires-Dist: jsonargparse[doc]; extra == "dev"
Requires-Dist: pre-commit>=2.19.0; extra == "dev"
Requires-Dist: tox>=3.25.0; extra == "dev"
Requires-Dist: build>=0.10.0; extra == "dev"
Provides-Extra: doc
Requires-Dist: Sphinx>=1.7.9; extra == "doc"
Requires-Dist: sphinx-rtd-theme>=1.2.2; extra == "doc"
Requires-Dist: autodocsumm>=0.1.10; extra == "doc"
Requires-Dist: sphinx-autodoc-typehints>=1.19.5; extra == "doc"
Provides-Extra: maintainer
Requires-Dist: bump2version>=0.5.11; extra == "maintainer"
Requires-Dist: twine>=4.0.2; extra == "maintainer"
Dynamic: license-file
